error_handler.py
prompts.py
exarp-0.2.2.dist-info/licenses/LICENSE
project_management_automation/__init__.py
project_management_automation/context_helpers.py
project_management_automation/interactive.py
project_management_automation/lifespan.py
project_management_automation/naming.py
project_management_automation/server.py
project_management_automation/version.py
project_management_automation/middleware/__init__.py
project_management_automation/middleware/access_control.py
project_management_automation/middleware/logging_middleware.py
project_management_automation/middleware/path_validation.py
project_management_automation/middleware/rate_limit.py
project_management_automation/middleware/security.py
project_management_automation/middleware/tool_filter.py
project_management_automation/resources/__init__.py
project_management_automation/resources/assignees.py
project_management_automation/resources/cache.py
project_management_automation/resources/capabilities.py
project_management_automation/resources/catalog.py
project_management_automation/resources/context_primer.py
project_management_automation/resources/hint_registry.py
project_management_automation/resources/history.py
project_management_automation/resources/list.py
project_management_automation/resources/memories.py
project_management_automation/resources/prompt_discovery.py
project_management_automation/resources/session.py
project_management_automation/resources/status.py
project_management_automation/resources/tasks.py
project_management_automation/resources/templates.py
project_management_automation/scripts/__init__.py
project_management_automation/scripts/automate_attribution_check.py
project_management_automation/scripts/automate_automation_opportunities.py
project_management_automation/scripts/automate_daily.py
project_management_automation/scripts/automate_dependency_security.py
project_management_automation/scripts/automate_docs_health_v2.py
project_management_automation/scripts/automate_external_tool_hints.py
exarp-0.2.2.dist-info/METADATA
exarp-0.2.2.dist-info/WHEEL
exarp-0.2.2.dist-info/entry_points.txt
exarp-0.2.2.dist-info/top_level.txt
exarp-0.2.2.dist-info/RECORD
