Metadata-Version: 2.4
Name: exarp
Version: 0.2.2
Summary: MCP server for project management automation - health scores, task alignment, security scanning
Author-email: David Lowes <lindog1@users.noreply.github.com>
License-Expression: MIT
Project-URL: Homepage, https://github.com/davidl71/project-management-automation
Project-URL: Repository, https://github.com/davidl71/project-management-automation
Project-URL: Documentation, https://github.com/davidl71/project-management-automation#readme
Project-URL: Issues, https://github.com/davidl71/project-management-automation/issues
Keywords: mcp,model-context-protocol,project-management,automation,ai-tools,fastmcp,task-management,code-health
Classifier: Development Status :: 4 - Beta
Classifier: Intended Audience :: Developers
Classifier: Operating System :: OS Independent
Classifier: Programming Language :: Python :: 3
Classifier: Programming Language :: Python :: 3.9
Classifier: Programming Language :: Python :: 3.10
Classifier: Programming Language :: Python :: 3.11
Classifier: Programming Language :: Python :: 3.12
Classifier: Topic :: Software Development :: Libraries :: Python Modules
Classifier: Topic :: Software Development :: Quality Assurance
Requires-Python: >=3.10
License-File: LICENSE
Requires-Dist: fastmcp>=2.0.0
Requires-Dist: pydantic>=2.0.0
Requires-Dist: mcp>=1.0.0
Requires-Dist: ollama>=0.1.0
Requires-Dist: mlx>=0.20.0
Requires-Dist: mlx-lm>=0.19.0
Requires-Dist: huggingface-hub>=0.20.0
Provides-Extra: dev
Requires-Dist: pytest>=7.0; extra == "dev"
Requires-Dist: pytest-cov>=4.0.0; extra == "dev"
Requires-Dist: pytest-mock>=3.10.0; extra == "dev"
Requires-Dist: pytest-asyncio>=0.21.0; extra == "dev"
Requires-Dist: coverage>=7.0.0; extra == "dev"
Requires-Dist: black>=23.0; extra == "dev"
Requires-Dist: mypy>=1.0; extra == "dev"
Requires-Dist: ruff>=0.1.0; extra == "dev"
Dynamic: license-file
